mpcontribs/io/archie/__init__.py
mpcontribs/io/archie/mpfile.py
mpcontribs/io/archie/test_archieml.txt
mpcontribs/io/archie/test_mpfile.py
mpcontribs/io/core/__init__.py
mpcontribs/io/core/mpfile.py
mpcontribs/io/core/recdict.py
mpcontribs/io/core/utils.py
mpcontribs/io/core/components/__init__.py
mpcontribs/io/core/components/gdata.py
mpcontribs/io/core/components/hdata.py
mpcontribs/io/core/components/sdata.py
mpcontribs/io/core/components/tdata.py
mpcontribs/io/core/components/test_components.py
mpcontribs/io/core/components/test_table.json
mpcontribs_io-2.2.2.dist-info/LICENSE
mpcontribs_io-2.2.2.dist-info/METADATA
mpcontribs_io-2.2.2.dist-info/WHEEL
mpcontribs_io-2.2.2.dist-info/top_level.txt
mpcontribs_io-2.2.2.dist-info/RECORD
