Metadata-Version: 2.1
Name: mpcontribs-io
Version: 2.2.2
Summary: MPContribs I/O Library
Home-page: https://github.com/materialsproject/MPContribs/tree/master/mpcontribs-io
Author: Patrick Huck
Author-email: phuck@lbl.gov
License: MIT
Platform: UNKNOWN
Requires-Dist: archieml
Requires-Dist: ipython
Requires-Dist: pandas
Requires-Dist: plotly
Requires-Dist: pymatgen
